LICENSE
jpgdl.py
jpgdl-0.1.4.dist-info/entry_points.txt
jpgdl-0.1.4.dist-info/LICENSE
jpgdl-0.1.4.dist-info/WHEEL
jpgdl-0.1.4.dist-info/METADATA
jpgdl-0.1.4.dist-info/RECORD
